srl/__init__.py
srl/_version.py
srl/ast/__init__.py
srl/ast/nodes.py
srl/cli/__init__.py
srl/cli/formatting.py
srl/cli/main.py
srl/engine/__init__.py
srl/engine/engine.py
srl/engine/expressions.py
srl/engine/rules.py
srl/engine/solutions.py
srl/engine/stratification.py
srl/parser/__init__.py
srl/parser/parser.py
srl/parser/transformer.py
srl/rdf/__init__.py
srl/rdf/namespace.py
srl/rdf/nodes.py
srl/py.typed
srl/parser/grammar.lark
shacl_rules-0.1.3.dist-info/METADATA
shacl_rules-0.1.3.dist-info/WHEEL
shacl_rules-0.1.3.dist-info/entry_points.txt
shacl_rules-0.1.3.dist-info/licenses/LICENSE
shacl_rules-0.1.3.dist-info/RECORD
