Metadata-Version: 2.4
Name: shacl-rules
Version: 0.1.3
Summary: Python SHACL 1.2 Rules (SRL) Parser and Evaluation Engine
Project-URL: Homepage, https://github.com/simonstey/py-srl
Project-URL: Repository, https://github.com/simonstey/py-srl
Project-URL: Issues, https://github.com/simonstey/py-srl/issues
Author-email: Simon Steyskal <simon.steyskal@siemens.com>
License-File: LICENSE
Keywords: RDF,SHACL,knowledge-graph,reasoning,rules,semantic-web
Classifier: Development Status :: 4 - Beta
Classifier: Intended Audience :: Developers
Classifier: Intended Audience :: Science/Research
Classifier: Programming Language :: Python :: 3
Classifier: Programming Language :: Python :: 3.12
Classifier: Topic :: Scientific/Engineering :: Artificial Intelligence
Classifier: Topic :: Software Development :: Libraries :: Python Modules
Requires-Python: >=3.12
Requires-Dist: click>=8.0.0
Requires-Dist: lark>=1.3.0
Requires-Dist: rdflib>=7.0.0
Requires-Dist: rich-click>=1.9.0
Requires-Dist: rich>=14.0.0
Provides-Extra: dev
Requires-Dist: black>=23.0; extra == 'dev'
Requires-Dist: isort>=5.12; extra == 'dev'
Requires-Dist: mypy>=1.0; extra == 'dev'
Requires-Dist: pytest-cov>=4.0; extra == 'dev'
Requires-Dist: pytest-xdist>=3.0; extra == 'dev'
Requires-Dist: pytest>=7.0; extra == 'dev'
Provides-Extra: docs
Requires-Dist: sphinx-rtd-theme>=1.3; extra == 'docs'
Requires-Dist: sphinx>=7.0; extra == 'docs'
